articlequality/__init__.py
articlequality/about.py
articlequality/articlequality.py
articlequality/extractors/__init__.py
articlequality/extractors/enwiki.py
articlequality/extractors/extractor.py
articlequality/extractors/frwiki.py
articlequality/extractors/ptwiki.py
articlequality/extractors/ruwiki.py
articlequality/extractors/svwiki.py
articlequality/extractors/trwiki.py
articlequality/extractors/ukwiki.py
articlequality/feature_lists/__init__.py
articlequality/feature_lists/enwiki.py
articlequality/feature_lists/euwiki.py
articlequality/feature_lists/fawiki.py
articlequality/feature_lists/frwiki.py
articlequality/feature_lists/frwikisource.py
articlequality/feature_lists/glwiki.py
articlequality/feature_lists/nlwiki.py
articlequality/feature_lists/ptwiki.py
articlequality/feature_lists/ruwiki.py
articlequality/feature_lists/svwiki.py
articlequality/feature_lists/trwiki.py
articlequality/feature_lists/ukwiki.py
articlequality/feature_lists/wikibase.py
articlequality/feature_lists/wikidatawiki.py
articlequality/feature_lists/wikipedia.py
articlequality/feature_lists/wikisource.py
articlequality/feature_lists/wikidatawiki_data/__init__.py
articlequality/feature_lists/wikidatawiki_data/items_lists.py
articlequality/feature_lists/wikidatawiki_data/property_datatypes.py
articlequality/utilities/__init__.py
articlequality/utilities/extract_from_text.py
articlequality/utilities/extract_labelings.py
articlequality/utilities/extract_scores.py
articlequality/utilities/extract_text.py
articlequality/utilities/fetch_item_info.py
articlequality/utilities/fetch_labels.py
articlequality/utilities/fetch_text.py
articlequality/utilities/score.py
articlequality/utilities/util.py
articlequality/utilities/weighted_sum.py
articlequality-0.4.4.dist-info/LICENSE
articlequality-0.4.4.dist-info/METADATA
articlequality-0.4.4.dist-info/WHEEL
articlequality-0.4.4.dist-info/entry_points.txt
articlequality-0.4.4.dist-info/top_level.txt
articlequality-0.4.4.dist-info/RECORD
