Metadata-Version: 2.1
Name: articlequality
Version: 0.4.4
Summary: A library for performing automatic detection of assessment classes of Wikipedia articles.
Home-page: https://github.com/wikimedia/articlequality
Author: Aaron Halfaker / Morten Warncke-Wang
Author-email: ahalfaker@wikimedia.org
License: MIT
Classifier: Development Status :: 4 - Beta
Classifier: Topic :: Software Development :: Libraries :: Python Modules
Classifier: Programming Language :: Python
Classifier: Programming Language :: Python :: 3
Classifier: Intended Audience :: Developers
Classifier: License :: OSI Approved :: MIT License
Classifier: Operating System :: OS Independent
Classifier: Topic :: Text Processing :: Linguistic
Classifier: Topic :: Text Processing :: General
Classifier: Topic :: Utilities
Classifier: Topic :: Scientific/Engineering
License-File: LICENSE
Requires-Dist: mwapi
Requires-Dist: mwbase (<0.1.999,>=0.1.0)
Requires-Dist: mwreverts
Requires-Dist: mwtypes
Requires-Dist: mwxml (>=0.3.3)
Requires-Dist: revscoring (<2.11.999,>=2.11.0)
